truncjson-1.2.12.dist-info/RECORD
truncjson-1.2.12.dist-info/LICENSE
truncjson-1.2.12.dist-info/WHEEL
truncjson-1.2.12.dist-info/top_level.txt
truncjson-1.2.12.dist-info/METADATA
truncjson/Stream.cpython-39-darwin.so
truncjson/version.py
truncjson/__init__.py
truncjson/__main__.py
truncjson/truncjson.cpython-39-darwin.so
